<?xml version="1.0" encoding="utf-8"?>
<PasswordPolicy xmlns:xsi="http://www.w3.org/2001/XMLSchema-instance" xmlns:xsd="http://www.w3.org/2001/XMLSchema">
  <PolicyName>Jeevan Anand</PolicyName>
  <PasswordLength>10</PasswordLength>
  <Complexity>6</Complexity>
  <DNAPrevious>6</DNAPrevious>
  <PswExpDate>25/08/2016</PswExpDate>
  <OTPExpMin>28</OTPExpMin>
  <NoInvalidAttempts>23</NoInvalidAttempts>
  <LockOutPeriod>45</LockOutPeriod>
  <LockType>2</LockType>
  <SendE_mail>true</SendE_mail>
  <ChangePswAftLogin>true</ChangePswAftLogin>
  <CannotChangePsw>false</CannotChangePsw>
  <OTPLogin>true</OTPLogin>
  <SendEmailOnLoginSuccess>true</SendEmailOnLoginSuccess>
  <SendEmailOnLoginFailur>true</SendEmailOnLoginFailur>
</PasswordPolicy>