<?xml version="1.0" encoding="utf-8"?>
<PasswordPolicy xmlns:xsi="http://www.w3.org/2001/XMLSchema-instance" xmlns:xsd="http://www.w3.org/2001/XMLSchema">
  <PolicyName>Jeevan Kishore</PolicyName>
  <PasswordLength>6</PasswordLength>
  <Complexity>4</Complexity>
  <DNAPrevious>6</DNAPrevious>
  <PswExpDate>28/08/2016</PswExpDate>
  <OTPExpMin>10</OTPExpMin>
  <NoInvalidAttempts>23</NoInvalidAttempts>
  <LockOutPeriod>15</LockOutPeriod>
  <LockType>2</LockType>
  <SendE_mail>true</SendE_mail>
  <ChangePswAftLogin>true</ChangePswAftLogin>
  <CannotChangePsw>false</CannotChangePsw>
  <OTPLogin>false</OTPLogin>
  <SendEmailOnLoginSuccess>true</SendEmailOnLoginSuccess>
  <SendEmailOnLoginFailur>true</SendEmailOnLoginFailur>
</PasswordPolicy>